cop_number/__init__.py
cop_number/cop.py
cop_number-1.1.2.dist-info/METADATA
cop_number-1.1.2.dist-info/WHEEL
cop_number-1.1.2.dist-info/license.txt
cop_number-1.1.2.dist-info/top_level.txt
cop_number-1.1.2.dist-info/RECORD
