Metadata-Version: 2.1
Name: cop-number
Version: 1.1.2
Summary: A NetworkX package solving k-FIXED COP NUMBER
Home-page: https://github.com/Jabbath/Cop-Number
Author: Anton Afanassiev
Author-email: antonafana@yahoo.ca
License: MIT
Download-URL: https://github.com/Jabbath/Cop-Number/archive/1.1.2.tar.gz
Keywords: graph,theory,cop,number,k-FIXED,cops,robbers,pursuit,evasion,search
Platform: UNKNOWN
Classifier: Development Status :: 5 - Production/Stable
Requires-Dist: networkx
